{
    "links": [
        {
            "type": "twitter",
            "title": "Twitter",
            "icon": "fa-twitter",
            "url": "https://twitter.com/markov_yuriy"
        },
        {
            "type": "github",
            "title": "GitHub",
            "icon": "fa-github",
            "url": "https://github.com/peacefullatom"
        },
        {
            "type": "devto",
            "title": "DEV",
            "icon": "fa-dev",
            "url": "https://dev.to/peacefullatom"
        }
    ]
}